LICENSE
README.md
setup.py
./worldtools/__init__.py
./worldtools/exceptions.py
./worldtools/player.py
./worldtools/util.py
./worldtools/backup/__init__.py
./worldtools/backup/chunks.py
./worldtools/nbt/__init__.py
./worldtools/nbt/parse.py
./worldtools/nbt/types.py
./worldtools/world/__init__.py
./worldtools/world/chunk.py
./worldtools/world/heightmap.py
./worldtools/world/region.py
./worldtools/world/world.py
worldtools/__init__.py
worldtools/exceptions.py
worldtools/player.py
worldtools/util.py
worldtools.egg-info/PKG-INFO
worldtools.egg-info/SOURCES.txt
worldtools.egg-info/dependency_links.txt
worldtools.egg-info/top_level.txt
worldtools/backup/__init__.py
worldtools/backup/chunks.py
worldtools/nbt/__init__.py
worldtools/nbt/parse.py
worldtools/nbt/types.py
worldtools/world/__init__.py
worldtools/world/chunk.py
worldtools/world/heightmap.py
worldtools/world/region.py
worldtools/world/world.py